Metadata-Version: 2.4
Name: twinshare
Version: 0.1.43
Summary: Twin Share - Environment Manager - narzędzie do dzielenia się środowiskami Embedded/AI/VM
Author: Tom Sapletta
Classifier: Development Status :: 3 - Alpha
Classifier: Intended Audience :: Developers
Classifier: License :: OSI Approved :: Apache Software License
Classifier: Programming Language :: Python :: 3
Classifier: Programming Language :: Python :: 3.8
Classifier: Programming Language :: Python :: 3.9
Classifier: Programming Language :: Python :: 3.10
Requires-Python: >=3.8
License-File: LICENSE
Requires-Dist: libvirt-python>=8.0.0
Requires-Dist: aiohttp[speedups]<4.0.0,>=3.8.0
Requires-Dist: aiohttp-cors>=0.7.0
Requires-Dist: asyncio>=3.4.3
Requires-Dist: tabulate>=0.9.0
Requires-Dist: pyyaml>=6.0
Requires-Dist: cryptography>=40.0.0
Requires-Dist: python-daemon>=3.0.0
Requires-Dist: netifaces>=0.11.0
Requires-Dist: zeroconf>=0.38.0
Provides-Extra: dev
Requires-Dist: pytest>=7.0.0; extra == "dev"
Requires-Dist: black>=23.0.0; extra == "dev"
Requires-Dist: isort>=5.12.0; extra == "dev"
Requires-Dist: mypy>=1.0.0; extra == "dev"
Provides-Extra: windows
Requires-Dist: pywin32>=300; extra == "windows"
Dynamic: license-file
Dynamic: requires-python
